tank_inspector/__init__.py
tank_inspector/drop_table.py
tank_inspector/external_inspection/__init__.py
tank_inspector/external_inspection/create_table_ei.py
tank_inspector/external_inspection/delete_ei.py
tank_inspector/external_inspection/display_ei.py
tank_inspector/external_inspection/insert_ei.py
tank_inspector/external_inspection/update_ei.py
tank_inspector/file_csv/__init__.py
tank_inspector/file_csv/display_csv.py
tank_inspector/file_csv/table_csv.py
tank_inspector/file_pdf/__init__.py
tank_inspector/file_pdf/create_table_pdf.py
tank_inspector/file_pdf/delete_pdf.py
tank_inspector/file_pdf/download_pdf.py
tank_inspector/file_pdf/insert_pdf.py
tank_inspector/pre_monsoon/__init__.py
tank_inspector/pre_monsoon/create_table_pm.py
tank_inspector/pre_monsoon/delete_pm.py
tank_inspector/pre_monsoon/display_pm.py
tank_inspector/pre_monsoon/insert_pm.py
tank_inspector/pre_monsoon/update_pm.py
tank_inspector-0.0.0.dist-info/METADATA
tank_inspector-0.0.0.dist-info/WHEEL
tank_inspector-0.0.0.dist-info/entry_points.txt
tank_inspector-0.0.0.dist-info/top_level.txt
tank_inspector-0.0.0.dist-info/RECORD
