Metadata-Version: 2.1
Name: tank-inspector
Version: 0.0.0
Summary: Database entry for student profile
Author: Sonarjit
